mmc_export/Formats/curseforge.py
mmc_export/Formats/modrinth.py
mmc_export/Formats/packwiz.py
mmc_export/Helpers/resourceAPI.py
mmc_export/Helpers/structures.py
mmc_export/Helpers/utils.py
mmc_export/__init__.py
mmc_export/__main__.py
mmc_export/config.py
mmc_export/main.py
mmc_export/parser.py
mmc_export-2.8.10.dist-info/LICENSE
mmc_export-2.8.10.dist-info/METADATA
mmc_export-2.8.10.dist-info/WHEEL
mmc_export-2.8.10.dist-info/entry_points.txt
mmc_export-2.8.10.dist-info/RECORD
