Metadata-Version: 2.3
Name: mmc-export
Version: 2.8.10
Summary: Export MMC modpack to other modpack formats
License: MIT
Keywords: minecraft,mods,modpack,converter,MultiMC
Author: RozeFound
Requires-Python: >=3.11,<4.0
Classifier: License :: OSI Approved :: MIT License
Classifier: Programming Language :: Python :: 3
Classifier: Programming Language :: Python :: 3.11
Classifier: Programming Language :: Python :: 3.12
Classifier: Programming Language :: Python :: 3.13
Requires-Dist: Werkzeug (>=2.2.2,<4.0.0)
Requires-Dist: aiohttp (>=3.8.3,<4.0.0)
Requires-Dist: aiohttp-client-cache[filesystem] (>=0.7.3,<0.12.0)
Requires-Dist: certifi (>=2025.8.3,<2026.0.0)
Requires-Dist: cryptography (>=41.0.3,<45.0.0)
Requires-Dist: keyring (>=23.11,<25.0)
Requires-Dist: murmurhash2 (>=0.2.10,<0.3.0)
Requires-Dist: tenacity (>=8.1.0,<9.0.0)
Requires-Dist: tomli-w (>=1.0.0,<2.0.0)
Requires-Dist: xxhash (>=3.1.0,<4.0.0)
Project-URL: Repository, https://github.com/RozeFound/mmc-export
